{"data": [{"traceID": "0d56ebf5c4991b91", "spans": [{"traceID": "0d56ebf5c4991b91", "spanID": "2b82198cddeecb39", "flags": 1, "operationName": "error", "references": [{"refType": "FOLLOWS_FROM", "traceID": "0d56ebf5c4991b91", "spanID": "0d56ebf5c4991b91"}], "startTime": 1657556483056000, "duration": 100274, "tags": [{"key": "internal.span.format", "type": "string", "value": "proto"}], "logs": [{"timestamp": 1657556483056000, "fields": [{"key": "event", "type": "string", "value": "preHandle"}, {"key": "handler", "type": "string", "value": "public org.springframework.http.ResponseEntity<java.util.Map<java.lang.String, java.lang.Object>> org.springframework.boot.autoconfigure.web.BasicErrorController.error(javax.servlet.http.HttpServletRequest)"}, {"key": "handler.class_simple_name", "type": "string", "value": "BasicErrorController"}, {"key": "handler.method_name", "type": "string", "value": "error"}]}, {"timestamp": 1657556483156000, "fields": [{"key": "event", "type": "string", "value": "afterCompletion"}, {"key": "handler", "type": "string", "value": "public org.springframework.http.ResponseEntity<java.util.Map<java.lang.String, java.lang.Object>> org.springframework.boot.autoconfigure.web.BasicErrorController.error(javax.servlet.http.HttpServletRequest)"}]}], "processID": "p1", "warnings": null}, {"traceID": "0d56ebf5c4991b91", "spanID": "0d56ebf5c4991b91", "flags": 1, "operationName": "DELETE", "references": [], "startTime": 1657556482454000, "duration": 501057, "tags": [{"key": "http.status_code", "type": "int64", "value": 404}, {"key": "component", "type": "string", "value": "java-web-servlet"}, {"key": "span.kind", "type": "string", "value": "server"}, {"key": "sampler.type", "type": "string", "value": "const"}, {"key": "sampler.param", "type": "bool", "value": true}, {"key": "http.url", "type": "string", "value": "http://admin-order-contest.apps.play.gepaplexx.com/api/v1/adminorderservice/adminorder/8744d45c-9079-4574-a6bb-b756e5233daa/"}, {"key": "http.method", "type": "string", "value": "DELETE"}, {"key": "internal.span.format", "type": "string", "value": "proto"}], "logs": [], "processID": "p1", "warnings": null}], "processes": {"p1": {"serviceName": "ts-admin-order-service", "tags": [{"key": "hostname", "type": "string", "value": "ts-admin-order-service-75f5cc4c4d-c8hn8"}, {"key": "ip", "type": "string", "value": "10.131.3.51"}, {"key": "jaeger.version", "type": "string", "value": "Java-0.30.6"}]}}, "warnings": null}, {"traceID": "4abb9da4ddcf2494", "spans": [{"traceID": "4abb9da4ddcf2494", "spanID": "959dbf390bf9ca2e", "flags": 1, "operationName": "PUT", "references": [{"refType": "CHILD_OF", "traceID": "4abb9da4ddcf2494", "spanID": "4abb9da4ddcf2494"}], "startTime": 1657556482057000, "duration": 96800, "tags": [{"key": "http.status_code", "type": "int64", "value": 200}, {"key": "component", "type": "string", "value": "java-spring-rest-template"}, {"key": "span.kind", "type": "string", "value": "client"}, {"key": "http.url", "type": "string", "value": "http://ts-order-other-service:12032/api/v1/orderOtherService/orderOther/admin"}, {"key": "peer.port", "type": "int64", "value": 12032}, {"key": "http.method", "type": "string", "value": "PUT"}, {"key": "internal.span.format", "type": "string", "value": "proto"}], "logs": [], "processID": "p1", "warnings": null}, {"traceID": "4abb9da4ddcf2494", "spanID": "3f262ad954bad758", "flags": 1, "operationName": "updateOrder", "references": [{"refType": "CHILD_OF", "traceID": "4abb9da4ddcf2494", "spanID": "959dbf390bf9ca2e"}], "startTime": 1657556482060000, "duration": 99305, "tags": [{"key": "http.status_code", "type": "int64", "value": 200}, {"key": "http.url", "type": "string", "value": "http://admin-order-contest.apps.play.gepaplexx.com/api/v1/orderOtherService/orderOther/admin"}, {"key": "component", "type": "string", "value": "java-web-servlet"}, {"key": "span.kind", "type": "string", "value": "server"}, {"key": "http.method", "type": "string", "value": "PUT"}, {"key": "internal.span.format", "type": "string", "value": "proto"}], "logs": [{"timestamp": 1657556482063000, "fields": [{"key": "event", "type": "string", "value": "preHandle"}, {"key": "handler", "type": "string", "value": "public org.springframework.http.HttpEntity other.controller.OrderOtherController.updateOrder(other.entity.Order,org.springframework.http.HttpHeaders)"}, {"key": "handler.class_simple_name", "type": "string", "value": "OrderOtherController"}, {"key": "handler.method_name", "type": "string", "value": "updateOrder"}]}, {"timestamp": 1657556482153000, "fields": [{"key": "event", "type": "string", "value": "afterCompletion"}, {"key": "handler", "type": "string", "value": "public org.springframework.http.HttpEntity other.controller.OrderOtherController.updateOrder(other.entity.Order,org.springframework.http.HttpHeaders)"}]}], "processID": "p2", "warnings": null}, {"traceID": "4abb9da4ddcf2494", "spanID": "4abb9da4ddcf2494", "flags": 1, "operationName": "updateOrder", "references": [], "startTime": 1657556481953000, "duration": 402028, "tags": [{"key": "http.status_code", "type": "int64", "value": 200}, {"key": "component", "type": "string", "value": "java-web-servlet"}, {"key": "span.kind", "type": "string", "value": "server"}, {"key": "sampler.type", "type": "string", "value": "const"}, {"key": "sampler.param", "type": "bool", "value": true}, {"key": "http.url", "type": "string", "value": "http://admin-order-contest.apps.play.gepaplexx.com/api/v1/adminorderservice/adminorder"}, {"key": "http.method", "type": "string", "value": "PUT"}, {"key": "internal.span.format", "type": "string", "value": "proto"}], "logs": [{"timestamp": 1657556482054000, "fields": [{"key": "event", "type": "string", "value": "preHandle"}, {"key": "handler", "type": "string", "value": "public org.springframework.http.HttpEntity adminorder.controller.AdminOrderController.updateOrder(adminorder.entity.Order,org.springframework.http.HttpHeaders)"}, {"key": "handler.class_simple_name", "type": "string", "value": "AdminOrderController"}, {"key": "handler.method_name", "type": "string", "value": "updateOrder"}]}, {"timestamp": 1657556482354000, "fields": [{"key": "event", "type": "string", "value": "afterCompletion"}, {"key": "handler", "type": "string", "value": "public org.springframework.http.HttpEntity adminorder.controller.AdminOrderController.updateOrder(adminorder.entity.Order,org.springframework.http.HttpHeaders)"}]}], "processID": "p1", "warnings": null}], "processes": {"p1": {"serviceName": "ts-admin-order-service", "tags": [{"key": "hostname", "type": "string", "value": "ts-admin-order-service-75f5cc4c4d-c8hn8"}, {"key": "ip", "type": "string", "value": "10.131.3.51"}, {"key": "jaeger.version", "type": "string", "value": "Java-0.30.6"}]}, "p2": {"serviceName": "ts-order-other-service", "tags": [{"key": "hostname", "type": "string", "value": "ts-order-other-service-594678cb45-fvndt"}, {"key": "ip", "type": "string", "value": "10.131.3.90"}, {"key": "jaeger.version", "type": "string", "value": "Java-0.30.6"}]}}, "warnings": null}, {"traceID": "f4aa8ec64f9ff05e", "spans": [{"traceID": "f4aa8ec64f9ff05e", "spanID": "a897df86a0062917", "flags": 1, "operationName": "addcreateNewOrder", "references": [{"refType": "CHILD_OF", "traceID": "f4aa8ec64f9ff05e", "spanID": "1eeb0795913895d7"}], "startTime": 1657556481357000, "duration": 106521, "tags": [{"key": "http.status_code", "type": "int64", "value": 200}, {"key": "http.url", "type": "string", "value": "http://admin-order-contest.apps.play.gepaplexx.com/api/v1/orderOtherService/orderOther/admin"}, {"key": "component", "type": "string", "value": "java-web-servlet"}, {"key": "span.kind", "type": "string", "value": "server"}, {"key": "http.method", "type": "string", "value": "POST"}, {"key": "internal.span.format", "type": "string", "value": "proto"}], "logs": [{"timestamp": 1657556481363000, "fields": [{"key": "event", "type": "string", "value": "preHandle"}, {"key": "handler", "type": "string", "value": "public org.springframework.http.HttpEntity other.controller.OrderOtherController.addcreateNewOrder(other.entity.Order,org.springframework.http.HttpHeaders)"}, {"key": "handler.class_simple_name", "type": "string", "value": "OrderOtherController"}, {"key": "handler.method_name", "type": "string", "value": "addcreateNewOrder"}]}, {"timestamp": 1657556481461000, "fields": [{"key": "event", "type": "string", "value": "afterCompletion"}, {"key": "handler", "type": "string", "value": "public org.springframework.http.HttpEntity other.controller.OrderOtherController.addcreateNewOrder(other.entity.Order,org.springframework.http.HttpHeaders)"}]}], "processID": "p1", "warnings": ["clock skew adjustment disabled; not applying calculated delta of -350.391ms"]}, {"traceID": "f4aa8ec64f9ff05e", "spanID": "1eeb0795913895d7", "flags": 1, "operationName": "POST", "references": [{"refType": "CHILD_OF", "traceID": "f4aa8ec64f9ff05e", "spanID": "f4aa8ec64f9ff05e"}], "startTime": 1657556480658000, "duration": 803739, "tags": [{"key": "http.status_code", "type": "int64", "value": 200}, {"key": "component", "type": "string", "value": "java-spring-rest-template"}, {"key": "span.kind", "type": "string", "value": "client"}, {"key": "http.url", "type": "string", "value": "http://ts-order-other-service:12032/api/v1/orderOtherService/orderOther/admin"}, {"key": "peer.port", "type": "int64", "value": 12032}, {"key": "http.method", "type": "string", "value": "POST"}, {"key": "internal.span.format", "type": "string", "value": "proto"}], "logs": [], "processID": "p2", "warnings": null}, {"traceID": "f4aa8ec64f9ff05e", "spanID": "f4aa8ec64f9ff05e", "flags": 1, "operationName": "addOrder", "references": [], "startTime": 1657556479958000, "duration": 1895836, "tags": [{"key": "http.status_code", "type": "int64", "value": 200}, {"key": "component", "type": "string", "value": "java-web-servlet"}, {"key": "span.kind", "type": "string", "value": "server"}, {"key": "sampler.type", "type": "string", "value": "const"}, {"key": "sampler.param", "type": "bool", "value": true}, {"key": "http.url", "type": "string", "value": "http://admin-order-contest.apps.play.gepaplexx.com/api/v1/adminorderservice/adminorder"}, {"key": "http.method", "type": "string", "value": "POST"}, {"key": "internal.span.format", "type": "string", "value": "proto"}], "logs": [{"timestamp": 1657556480160000, "fields": [{"key": "event", "type": "string", "value": "preHandle"}, {"key": "handler", "type": "string", "value": "public org.springframework.http.HttpEntity adminorder.controller.AdminOrderController.addOrder(adminorder.entity.Order,org.springframework.http.HttpHeaders)"}, {"key": "handler.class_simple_name", "type": "string", "value": "AdminOrderController"}, {"key": "handler.method_name", "type": "string", "value": "addOrder"}]}, {"timestamp": 1657556481758000, "fields": [{"key": "event", "type": "string", "value": "afterCompletion"}, {"key": "handler", "type": "string", "value": "public org.springframework.http.HttpEntity adminorder.controller.AdminOrderController.addOrder(adminorder.entity.Order,org.springframework.http.HttpHeaders)"}]}], "processID": "p2", "warnings": null}], "processes": {"p1": {"serviceName": "ts-order-other-service", "tags": [{"key": "hostname", "type": "string", "value": "ts-order-other-service-594678cb45-fvndt"}, {"key": "ip", "type": "string", "value": "10.131.3.90"}, {"key": "jaeger.version", "type": "string", "value": "Java-0.30.6"}]}, "p2": {"serviceName": "ts-admin-order-service", "tags": [{"key": "hostname", "type": "string", "value": "ts-admin-order-service-75f5cc4c4d-c8hn8"}, {"key": "ip", "type": "string", "value": "10.131.3.51"}, {"key": "jaeger.version", "type": "string", "value": "Java-0.30.6"}]}}, "warnings": null}, {"traceID": "a0f594d14754fa0c", "spans": [{"traceID": "a0f594d14754fa0c", "spanID": "73a3d502209d11e3", "flags": 1, "operationName": "findAllOrder", "references": [{"refType": "CHILD_OF", "traceID": "a0f594d14754fa0c", "spanID": "61a95cfcc1ad7ec0"}], "startTime": 1657556477454000, "duration": 401913, "tags": [{"key": "http.status_code", "type": "int64", "value": 200}, {"key": "http.url", "type": "string", "value": "http://admin-order-contest.apps.play.gepaplexx.com/api/v1/orderOtherService/orderOther"}, {"key": "component", "type": "string", "value": "java-web-servlet"}, {"key": "span.kind", "type": "string", "value": "server"}, {"key": "http.method", "type": "string", "value": "GET"}, {"key": "internal.span.format", "type": "string", "value": "proto"}], "logs": [{"timestamp": 1657556477759000, "fields": [{"key": "event", "type": "string", "value": "preHandle"}, {"key": "handler", "type": "string", "value": "public org.springframework.http.HttpEntity other.controller.OrderOtherController.findAllOrder(org.springframework.http.HttpHeaders)"}, {"key": "handler.class_simple_name", "type": "string", "value": "OrderOtherController"}, {"key": "handler.method_name", "type": "string", "value": "findAllOrder"}]}, {"timestamp": 1657556477767000, "fields": [{"key": "event", "type": "string", "value": "afterCompletion"}, {"key": "handler", "type": "string", "value": "public org.springframework.http.HttpEntity other.controller.OrderOtherController.findAllOrder(org.springframework.http.HttpHeaders)"}]}], "processID": "p1", "warnings": ["clock skew adjustment disabled; not applying calculated delta of -92.9185ms"]}, {"traceID": "a0f594d14754fa0c", "spanID": "27f3bb260ad0de8b", "flags": 1, "operationName": "GET", "references": [{"refType": "CHILD_OF", "traceID": "a0f594d14754fa0c", "spanID": "a0f594d14754fa0c"}], "startTime": 1657556473861000, "duration": 2894156, "tags": [{"key": "http.status_code", "type": "int64", "value": 200}, {"key": "component", "type": "string", "value": "java-spring-rest-template"}, {"key": "span.kind", "type": "string", "value": "client"}, {"key": "http.url", "type": "string", "value": "http://ts-order-service:12031/api/v1/orderservice/order"}, {"key": "peer.port", "type": "int64", "value": 12031}, {"key": "http.method", "type": "string", "value": "GET"}, {"key": "internal.span.format", "type": "string", "value": "proto"}], "logs": [], "processID": "p2", "warnings": null}, {"traceID": "a0f594d14754fa0c", "spanID": "61a95cfcc1ad7ec0", "flags": 1, "operationName": "GET", "references": [{"refType": "CHILD_OF", "traceID": "a0f594d14754fa0c", "spanID": "a0f594d14754fa0c"}], "startTime": 1657556477357000, "duration": 410076, "tags": [{"key": "http.status_code", "type": "int64", "value": 200}, {"key": "component", "type": "string", "value": "java-spring-rest-template"}, {"key": "span.kind", "type": "string", "value": "client"}, {"key": "http.url", "type": "string", "value": "http://ts-order-other-service:12032/api/v1/orderOtherService/orderOther"}, {"key": "peer.port", "type": "int64", "value": 12032}, {"key": "http.method", "type": "string", "value": "GET"}, {"key": "internal.span.format", "type": "string", "value": "proto"}], "logs": [], "processID": "p2", "warnings": null}, {"traceID": "a0f594d14754fa0c", "spanID": "a0f594d14754fa0c", "flags": 1, "operationName": "getAllOrders", "references": [], "startTime": 1657556470553000, "duration": 9302774, "tags": [{"key": "http.status_code", "type": "int64", "value": 200}, {"key": "component", "type": "string", "value": "java-web-servlet"}, {"key": "span.kind", "type": "string", "value": "server"}, {"key": "sampler.type", "type": "string", "value": "const"}, {"key": "sampler.param", "type": "bool", "value": true}, {"key": "http.url", "type": "string", "value": "http://admin-order-contest.apps.play.gepaplexx.com/api/v1/adminorderservice/adminorder"}, {"key": "http.method", "type": "string", "value": "GET"}, {"key": "internal.span.format", "type": "string", "value": "proto"}], "logs": [{"timestamp": 1657556472656000, "fields": [{"key": "event", "type": "string", "value": "preHandle"}, {"key": "handler", "type": "string", "value": "public org.springframework.http.HttpEntity adminorder.controller.AdminOrderController.getAllOrders(org.springframework.http.HttpHeaders)"}, {"key": "handler.class_simple_name", "type": "string", "value": "AdminOrderController"}, {"key": "handler.method_name", "type": "string", "value": "getAllOrders"}]}, {"timestamp": 1657556479562000, "fields": [{"key": "event", "type": "string", "value": "afterCompletion"}, {"key": "handler", "type": "string", "value": "public org.springframework.http.HttpEntity adminorder.controller.AdminOrderController.getAllOrders(org.springframework.http.HttpHeaders)"}]}], "processID": "p2", "warnings": null}], "processes": {"p1": {"serviceName": "ts-order-other-service", "tags": [{"key": "hostname", "type": "string", "value": "ts-order-other-service-594678cb45-fvndt"}, {"key": "ip", "type": "string", "value": "10.131.3.90"}, {"key": "jaeger.version", "type": "string", "value": "Java-0.30.6"}]}, "p2": {"serviceName": "ts-admin-order-service", "tags": [{"key": "hostname", "type": "string", "value": "ts-admin-order-service-75f5cc4c4d-c8hn8"}, {"key": "ip", "type": "string", "value": "10.131.3.51"}, {"key": "jaeger.version", "type": "string", "value": "Java-0.30.6"}]}}, "warnings": null}], "total": 0, "limit": 0, "offset": 0, "errors": null}